lantern/__init__.py
lantern/__main__.py
lantern/utils.py
lantern/data/__init__.py
lantern/data/cfgen.py
lantern/data/data_cufflinks.py
lantern/data/data_sklearn.py
lantern/data/other.py
lantern/extensions/__init__.py
lantern/extensions/savehooks/__init__.py
lantern/extensions/savehooks/convert_to_script.py
lantern/extensions/savehooks/remove_output.py
lantern/grids/__init__.py
lantern/grids/grid_ipysheet.py
lantern/grids/grid_lineup.py
lantern/grids/grid_phosphor.py
lantern/grids/grid_plotly.py
lantern/grids/grid_psp.py
lantern/grids/grid_qgrid.py
lantern/plotting/__init__.py
lantern/plotting/plot_altair.py
lantern/plotting/plot_bokeh.py
lantern/plotting/plot_bqplot.py
lantern/plotting/plot_matplotlib.py
lantern/plotting/plot_nvd3.py
lantern/plotting/plot_perspective.py
lantern/plotting/plot_plotly.py
lantern/plotting/plotobj.py
lantern/plotting/plotutils.py
lantern/widgets/__init__.py
lantern/widgets/variable_inspector.py
tests/data/__init__.py
tests/data/test_all.py
tests/extensions/__init__.py
tests/grid/__init__.py
tests/grid/test_grid_plotly.py
tests/grid/test_grid_psp.py
tests/grid/test_grid_qgrid.py
tests/plot/__init__.py
tests/plot/test_plot.py
tests/plot/test_plot_bokeh.py
tests/plot/test_plot_matplotlib.py
tests/plot/test_plot_plotly.py
pylantern-0.1.6.dist-info/LICENSE
pylantern-0.1.6.dist-info/METADATA
pylantern-0.1.6.dist-info/WHEEL
pylantern-0.1.6.dist-info/top_level.txt
pylantern-0.1.6.dist-info/RECORD
