Metadata-Version: 2.1
Name: pylantern
Version: 0.1.6
Summary: Analytics library
Home-page: https://github.com/timkpaine/lantern
Author: Tim Paine
Author-email: timothy.k.paine@gmail.com
License: Apache 2.0
Download-URL: https://github.com/timkpaine/lantern/archive/v0.1.5.tar.gz
Keywords: analytics tools plotting
Platform: UNKNOWN
Classifier: Development Status :: 3 - Alpha
Classifier: Programming Language :: Python :: 3
Classifier: Programming Language :: Python :: 3.6
Classifier: Programming Language :: Python :: 3.7
Classifier: Programming Language :: Python :: 3.8
Requires-Dist: bokeh (>=1.0.2)
Requires-Dist: bs4 (>=0.0.1)
Requires-Dist: cufflinks (>=0.14.4)
Requires-Dist: Faker (>=1.0.1)
Requires-Dist: finance-enums (>=0.1.0)
Requires-Dist: future (>=0.17.1)
Requires-Dist: ipysheet (>=0.2.0)
Requires-Dist: ipywidgets (>=7.4.2)
Requires-Dist: jupyterlab (>=0.35.4)
Requires-Dist: lineup-widget (>=1.0.7)
Requires-Dist: matplotlib (>=3.0.2)
Requires-Dist: mimesis (>=3.0.0)
Requires-Dist: numpy (>=1.15.4)
Requires-Dist: pandas (>=0.23.4)
Requires-Dist: perspective-python (<0.4.0,>=0.1.2)
Requires-Dist: plotly (>=4.0.0)
Requires-Dist: qgrid (>=1.1.1)
Requires-Dist: scipy (>=1.2.0)
Requires-Dist: seaborn (>=0.9.0)
Requires-Dist: sidecar (>=0.2.0)
Requires-Dist: six (>=1.12.0)
Requires-Dist: scikit-learn (>=0.21.3)
Requires-Dist: ujson (>=1.35)
Requires-Dist: websocket-client (>=0.54.0)
Provides-Extra: dev
Requires-Dist: bokeh (>=1.0.2) ; extra == 'dev'
Requires-Dist: bs4 (>=0.0.1) ; extra == 'dev'
Requires-Dist: cufflinks (>=0.14.4) ; extra == 'dev'
Requires-Dist: Faker (>=1.0.1) ; extra == 'dev'
Requires-Dist: finance-enums (>=0.1.0) ; extra == 'dev'
Requires-Dist: future (>=0.17.1) ; extra == 'dev'
Requires-Dist: ipysheet (>=0.2.0) ; extra == 'dev'
Requires-Dist: ipywidgets (>=7.4.2) ; extra == 'dev'
Requires-Dist: jupyterlab (>=0.35.4) ; extra == 'dev'
Requires-Dist: lineup-widget (>=1.0.7) ; extra == 'dev'
Requires-Dist: matplotlib (>=3.0.2) ; extra == 'dev'
Requires-Dist: mimesis (>=3.0.0) ; extra == 'dev'
Requires-Dist: numpy (>=1.15.4) ; extra == 'dev'
Requires-Dist: pandas (>=0.23.4) ; extra == 'dev'
Requires-Dist: perspective-python (<0.4.0,>=0.1.2) ; extra == 'dev'
Requires-Dist: plotly (>=4.0.0) ; extra == 'dev'
Requires-Dist: qgrid (>=1.1.1) ; extra == 'dev'
Requires-Dist: scipy (>=1.2.0) ; extra == 'dev'
Requires-Dist: seaborn (>=0.9.0) ; extra == 'dev'
Requires-Dist: sidecar (>=0.2.0) ; extra == 'dev'
Requires-Dist: six (>=1.12.0) ; extra == 'dev'
Requires-Dist: scikit-learn (>=0.21.3) ; extra == 'dev'
Requires-Dist: ujson (>=1.35) ; extra == 'dev'
Requires-Dist: websocket-client (>=0.54.0) ; extra == 'dev'
Requires-Dist: pytest ; extra == 'dev'
Requires-Dist: pytest-cov ; extra == 'dev'
Requires-Dist: pylint ; extra == 'dev'
Requires-Dist: flake8 ; extra == 'dev'
Requires-Dist: mock ; extra == 'dev'
Requires-Dist: codecov ; extra == 'dev'
Requires-Dist: autopep8 ; extra == 'dev'
